google/cloud/video/stitcher/__init__.py
google/cloud/video/stitcher/gapic_version.py
google/cloud/video/stitcher/py.typed
google/cloud/video/stitcher_v1/__init__.py
google/cloud/video/stitcher_v1/gapic_metadata.json
google/cloud/video/stitcher_v1/gapic_version.py
google/cloud/video/stitcher_v1/py.typed
google/cloud/video/stitcher_v1/services/__init__.py
google/cloud/video/stitcher_v1/services/video_stitcher_service/__init__.py
google/cloud/video/stitcher_v1/services/video_stitcher_service/async_client.py
google/cloud/video/stitcher_v1/services/video_stitcher_service/client.py
google/cloud/video/stitcher_v1/services/video_stitcher_service/pagers.py
google/cloud/video/stitcher_v1/services/video_stitcher_service/transports/__init__.py
google/cloud/video/stitcher_v1/services/video_stitcher_service/transports/base.py
google/cloud/video/stitcher_v1/services/video_stitcher_service/transports/grpc.py
google/cloud/video/stitcher_v1/services/video_stitcher_service/transports/grpc_asyncio.py
google/cloud/video/stitcher_v1/services/video_stitcher_service/transports/rest.py
google/cloud/video/stitcher_v1/services/video_stitcher_service/transports/rest_base.py
google/cloud/video/stitcher_v1/types/__init__.py
google/cloud/video/stitcher_v1/types/ad_tag_details.py
google/cloud/video/stitcher_v1/types/cdn_keys.py
google/cloud/video/stitcher_v1/types/companions.py
google/cloud/video/stitcher_v1/types/events.py
google/cloud/video/stitcher_v1/types/fetch_options.py
google/cloud/video/stitcher_v1/types/live_configs.py
google/cloud/video/stitcher_v1/types/sessions.py
google/cloud/video/stitcher_v1/types/slates.py
google/cloud/video/stitcher_v1/types/stitch_details.py
google/cloud/video/stitcher_v1/types/video_stitcher_service.py
google/cloud/video/stitcher_v1/types/vod_configs.py
google_cloud_video_stitcher-0.10.0.dist-info/licenses/LICENSE
google_cloud_video_stitcher-0.10.0.dist-info/METADATA
google_cloud_video_stitcher-0.10.0.dist-info/WHEEL
google_cloud_video_stitcher-0.10.0.dist-info/top_level.txt
google_cloud_video_stitcher-0.10.0.dist-info/RECORD
